wpm_probability/Binomialdistribution.py
wpm_probability/Gaussiandistribution.py
wpm_probability/Generaldistribution.py
wpm_probability/__init__.py
wpm_probability-0.1.1.dist-info/METADATA
wpm_probability-0.1.1.dist-info/WHEEL
wpm_probability-0.1.1.dist-info/top_level.txt
wpm_probability-0.1.1.dist-info/RECORD
