Metadata-Version: 2.1
Name: wpm-probability
Version: 0.1.1
Summary: Probability distributions objects: Gaussian, Binomial.
Home-page: https://github.com/WisnuMulya/Probability-Distribution-Package
Author: Wisnu Mulya
Author-email: wisnu@wisnumulya.com
License: MIT License
Platform: UNKNOWN
Requires-Dist: matplotlib
